pepperize_projen_awscdk_construct/__init__.py
pepperize_projen_awscdk_construct/py.typed
pepperize_projen_awscdk_construct/_jsii/__init__.py
pepperize_projen_awscdk_construct/_jsii/projen-awscdk-construct@0.0.730.jsii.tgz
pepperize.projen_awscdk_construct-0.0.730.dist-info/LICENSE
pepperize.projen_awscdk_construct-0.0.730.dist-info/METADATA
pepperize.projen_awscdk_construct-0.0.730.dist-info/WHEEL
pepperize.projen_awscdk_construct-0.0.730.dist-info/top_level.txt
pepperize.projen_awscdk_construct-0.0.730.dist-info/RECORD
