Metadata-Version: 2.1
Name: pepperize.projen-awscdk-construct
Version: 0.0.730
Summary: This project provides a projen project type providing presets for an AWS CDK construct library project
Home-page: https://github.com/pepperize/projen-awscdk-construct.git
Author: Patrick Florek<patrick.florek@gmail.com>
License: MIT
Project-URL: Source, https://github.com/pepperize/projen-awscdk-construct.git
Classifier: Intended Audience :: Developers
Classifier: Operating System :: OS Independent
Classifier: Programming Language :: JavaScript
Classifier: Programming Language :: Python :: 3 :: Only
Classifier: Programming Language :: Python :: 3.8
Classifier: Programming Language :: Python :: 3.9
Classifier: Programming Language :: Python :: 3.10
Classifier: Programming Language :: Python :: 3.11
Classifier: Typing :: Typed
Classifier: Development Status :: 5 - Production/Stable
Classifier: License :: OSI Approved
Requires-Python: ~=3.8
License-File: LICENSE
Requires-Dist: jsii<2.0.0,>=1.106.0
Requires-Dist: projen<0.92.0,>=0.91.1
Requires-Dist: publication>=0.0.3
Requires-Dist: typeguard<4.3.0,>=2.13.3
